setup.cfg
setup.py
httm/__init__.py
httm.egg-info/PKG-INFO
httm.egg-info/SOURCES.txt
httm.egg-info/dependency_links.txt
httm.egg-info/requires.txt
httm.egg-info/top_level.txt
httm/data/default_start_of_line_ringing.npz
httm/data/simulated_pattern_noise.fits
httm/data_structures/__init__.py
httm/data_structures/common.py
httm/data_structures/documentation.py
httm/data_structures/electron_flux_converter.py
httm/data_structures/metadata.py
httm/data_structures/raw_converter.py
httm/fits_utilities/__init__.py
httm/fits_utilities/electron_flux_fits.py
httm/fits_utilities/header_tools.py
httm/fits_utilities/raw_fits.py
httm/resource_utilities/__init__.py
httm/system/__init__.py
httm/system/config_file.py
httm/system/command_line/__init__.py
httm/system/command_line/metadata.py
httm/transformations/__init__.py
httm/transformations/common.py
httm/transformations/constants.py
httm/transformations/electron_flux_converters_to_raw.py
httm/transformations/electron_flux_slices_to_raw.py
httm/transformations/metadata.py
httm/transformations/raw_converters_to_calibrated.py
httm/transformations/raw_slices_to_calibrated.py
scripts/electron_flux_single_ccd_ffi_to_simulated_raw
scripts/raw_single_ccd_ffi_to_calibrated_electron_flux