Metadata-Version: 1.1
Name: httm
Version: 0.2.2
Summary: A transformation library for RAW and Electron Flux TESS Images
Home-page: https://github.com/TESScience/httm
Author: Matthew Wampler-Doty, John Doty
Author-email: matthew.wampler.doty@gmail.com, jpd@noqsi.com
License: UNKNOWN
Download-URL: https://github.com/TESScience/httm/tarball/0.2.2
Platform: UNKNOWN
